{
  "version": "0.28.10",
  "fixedMainScript": "./index.js",
  "builder": {
    "transforms": [
      "jsx",
      "imports",
      "typescript"
    ],
    "ignorePackages": [
      "ual"
    ],
    "ignoreSources": [
      "./src/verbosity/index.js"
    ]
  },
  "publish": {
    "include": [
      "./dist"
    ]
  },
  "development": {
    "headPackage": "corenode",
    "originGit": "https://github.com/ragestudio/corenode",
    "docs": [
      "corenode",
      "utils"
    ],
    "dockerImageName": "srgooglo/corenode"
  }
}
